{
  "name": "Winifred Jordan",
  "age": 49,
  "address": {
    "street": "Gedu Drive",
    "city": "Koznecriw",
    "state": "CT",
    "zip": "94986"
  },
  "contact": {
    "phone": "(303) 888-5637",
    "servicePhone": "800615826"
  },
  "birthday": "1959-05-06T12:58:03.211Z",
  "ip": "61.221.221.125",
  "foo": "bar",
  "profile": {
    "about": "Lihhud ti takikcud fosruh feljicaza tij ohi ogtawu giegutal mus ticu gises wicer tir civozmo osu vaezsa nofamu. Te re witem merapi eli cerkaf mace ropeh kehse hoode tumud zedle cuzkav zajijup. Vemgah seprogdoz zan be pegtig ke je vaowejo faf da wonoz je pujub tul fic oterif du. Uvare boha houjku wus ofeaje povso mimof se uh sazfoh hilgu lovrifnop jiseeh bovdo caki gam hag.",
    "bio": "Olbuses ipe nuwobeh pepanef holluda riwfu faka pepzi han guret deijjuw foopfu padapgin sedsi zi aze. Udbaozi soloz op tedelha pog ezabu jem ehadeg pe kuhtatu ivtab pokbampop wufesu tur poruveze kajiv hugteuza. Ut fanewe zikdul dugdun nojuse pande ravjabo sazsan daukaevo epudawac fa dakinar zij lijosigu udwo lilehud ki. Buco ijja at liizfaj kehkevit oj ozolikcu me ca javazo rijjada zaafuol du da. Ho sosowaca fan vinluek orimi cabujuv dig fap doha ca tag macmimca hewo."
  },
  "apiKey": "627fa5b23486a7831011e23374e529cb00f976293dd5fe49f7f3c33c2a15b0e8",
  "currency": {
    "code": "ETB",
    "name": "Ethiopia Birr"
  }
}