{
  "name": "Floyd Douglas",
  "age": 60,
  "address": {
    "street": "Hubi Point",
    "city": "Duheof",
    "state": "TX",
    "zip": "23632"
  },
  "contact": {
    "phone": "(346) 924-5529",
    "servicePhone": "800891766"
  },
  "birthday": "1961-02-14T15:58:15.114Z",
  "ip": "63.134.114.71",
  "foo": "bar",
  "profile": {
    "about": "Esogub ka lu fitza uvo fi dufozco lihu sibwiduva fa luva wa. Erwurfen anwi effin fe fa ek ne cordapof fi wiwro cudeik selnam suuw lawpuz fabzasus burhaz zekjaz. Doefiha ru jekota sipnor cefadja teru jegojdow bifedtid merake mohkob koj idiit ko.",
    "bio": "Wig racah id gu hitwod sizur ajla bojub ujmigrec pi roawjag uhafwu ja ha jus. Gahab fu ikawedas lih gosopviz nut paowimeg mihiib fe vegni pi zais ite dofelof dezohva ewfuvge kunle cikuk. Ahawo ahpocfuw mew vekdubpif canek rodunow fu deih siknupcu we madruug pomti. Damnosuj juzu orainpu jutlegad upgu vag noguluri hepnunruc loute zatto relhismi tujudu ahiwavad."
  },
  "apiKey": "3ede2a636e6e6f096b516982e43bf8ac6c2508fa4d45dc673454747ce8d0b73b",
  "currency": {
    "code": "CAD",
    "name": "Canada Dollar"
  }
}