{
  "name": "Bessie Watson",
  "age": 28,
  "address": {
    "street": "Dijato Path",
    "city": "Jutuskup",
    "state": "KY",
    "zip": "74934"
  },
  "contact": {
    "phone": "(423) 967-3001",
    "servicePhone": "800757592"
  },
  "birthday": "1982-05-18T07:29:36.570Z",
  "ip": "203.158.30.85",
  "foo": "bar",
  "profile": {
    "about": "Ka ela utpog hiva hihigiw keba todi zoveuci re ozsa zahveda foniwih ophevhoz voga liwi. Toton ufdamu memtak si or do elica subuzcun ga mifve ku jomru fumhensus si lotawohiv ra wipa fowoob. Ohabojbav fibjizlil hepviwja zarpirug zise oheugi zoj itgo la zurij cicdocev er etulukbe hop no rivaruka. Men nijacci felarufe bazufedi not zeki leawefof adhu isaojre in nuhnihij zujak su uj runo ra. Jifiluwo tiudiew gozkig dekubaz ve ter jezog fori vabab kecu fi jihef.",
    "bio": "Ka havad afufafku vuca of biw gemev dajiwfo eteudusoc ok iwawi wa cumes juv amo puz sinot rulhenuz. Ejetun naz pelzo ab je becom civ wejikiz monsucep kamobte ude va vocuti zaileobi kizod nah. Fogerser wew ne wejut pepim gisoj cocjuf cidcaelo noksi galrongi ejhusil ceja bicbap ozjev. Jalzu ir nofat mebigce pefusako igani laeme azatetatu naglan mi fonkalkac gipeva. Amsijnos isaasnah zoltejgu avo eslurgoc sa jemojwuk bo se tabiw un feppalu upodisaw cuikiin hoj ok pisocho."
  },
  "apiKey": "fd240cdcbbcb65ed92fb65f91d8faf09e8bed2f0b8c8127415c4d20e2684c67d",
  "currency": {
    "code": "NAD",
    "name": "Namibia Dollar"
  }
}