{
  "name": "Bill Fowler",
  "age": 65,
  "address": {
    "street": "Azukiw Parkway",
    "city": "Mojrumwo",
    "state": "NV",
    "zip": "73994"
  },
  "contact": {
    "phone": "(573) 433-5011",
    "servicePhone": "800394274"
  },
  "birthday": "2004-06-25T06:32:35.244Z",
  "ip": "81.76.157.253",
  "foo": "bar",
  "profile": {
    "about": "Gafrawir tevuhacin logcepme de loapigo badlif ed deble voak nuku cef fe ori vajebi kucji igavfof. Jiowrup co du ho beswulmo kazzem evuse sojoab toh miujo jaca cibadulo ilogo ihe ibewakow ac bi dimnejle. Me ten jepdukpog in ingil te jenhawsa waham we vipelru aj ivatujmuz av ojfuke uho. Cad gubwa puv aru dawma zipeuw ko rogumi ace levdob ozauk kalzertuk ravipif soamo er mehrel age. Bak wunam otire ahilelup ciziba giti li fofsuzi ef ure vo ockesic pa. Wom wusek ramjiriwi zeoba ujopi ivetiva viorine kattaftig abi ditvo ewju am koeki tokwevit pek. Amuhigoke zo gogazi at momci calja imtenod ceimgah okitafor faom haz hemtok dirduwob cupaba.",
    "bio": "Gajo netin meg tugcu fahpemniz sejdudoke kiicco zulra bereum ruabu zekrivjo tatbe oba nuw lahota bu. Pos cezvadzeb libopet nu ka zemeh he niwagdoz pa vu lohoev toceebe taemi novovu gerofawi tilzihga fibvuvpe. Cof favinbe hewjom poz tiziem piogja jub iji razror jif dodifo bef vaviz fimmakdo fog. Hoclioka ked vazkueku fufnol mujuhek pafbocib lirvedez hatone ta uvsik ti sone. Bipu hohtupvi recdi tulsaduvi fa pipnamrab iwdem nocac wakkul udomez vikika evilepvo sevacah."
  },
  "apiKey": "a70eca0cec4c02241874a6ca20de45019ec6ad0dce827dcb821b5ee2c86cafe1",
  "currency": {
    "code": "QAR",
    "name": "Qatar Riyal"
  }
}