{
  "name": "Clayton Jimenez",
  "age": 28,
  "address": {
    "street": "Ekhi Heights",
    "city": "Agkadaci",
    "state": "ND",
    "zip": "85493"
  },
  "contact": {
    "phone": "(951) 209-3441",
    "servicePhone": "800995681"
  },
  "birthday": "1980-08-10T03:12:02.361Z",
  "ip": "133.255.168.118",
  "foo": "bar",
  "profile": {
    "about": "Ec puha bi fubvoz meas ufu talfivit zika mawusi gebru utonnop cuh si lowu mosfuge wewwup muetagof guk. Fibte wig tic wew tupuwe javesoj ofwotoc fekpen nelecahos mof ovadov ced ez cemih vozobwuc. Dejof vejoj lauki idihufu feeg deijuhec cez jih omo givoc cu cetpa ku. Go irocupama wuw iwsacofo dici udce gep nagev ubaho mahup puap fagzimed fespu ewi posnuwref ilube.",
    "bio": "Pahu dewaztuh tekutvaw wacefun lagona cozenwut bozro suamu lacrigiz pac apaj luc uklod. Lo el awabutki ozudanzu ena vim ib favzahe vic gup ifuma daf. Gif deje jehojes ev arhi cimjuc zika haocoz vukitka upupiuza hitgakbib zovimeh. Racopa lapdo af cu ejofcap fitzen rimgewjaj zoeg kajon avdadev femeho tow azgadwab puin ama he. Ce jal jo ucapozfuf onsi jeljakjel ror hori ajo rivi zevela dutalabez dezihbef war nel beil. Fe horjip pembereg mofpev mewal fit huzec ofsovija vevuta mokbuzzo rupun doz co."
  },
  "apiKey": "7e44d137e437fbb363109288fbf921363e3f3d48120336aee597057345d7fd45",
  "currency": {
    "code": "XCD",
    "name": "East Caribbean Dollar"
  }
}